{
  "metainfo" : {
    "migrationVersions" : {
      "gemBuilderVersion" : "v1"
    },
    "functions" : { },
    "codeGenConfiguration" : {
      "editableConfig" : true,
      "plibVersion" : {
        "mavenVersion" : "8.2.1",
        "pyPiVersion" : "1.9.16"
      }
    },
    "id" : "1",
    "uri" : "pipelines/FilePathParse",
    "pipelineSettingsInfo" : {
      "applicationName" : "FilePathParse",
      "hasApplication" : true,
      "isFunctionsPackageDirDefined" : true
    },
    "language" : "python",
    "fabricId" : "9631",
    "frontEndLanguage" : "sql",
    "mode" : "batch",
    "udfs" : {
      "language" : "python",
      "udfs" : [ ],
      "functionPackageName" : "archer.archer.functions",
      "sharedFunctionPackageNames" : [ "prophecy.spark_basic.functions", "prophecy.streaming.functions", "prophecy.warehouse.functions" ]
    },
    "udafs" : {
      "language" : "python",
      "code" : ""
    },
    "configuration" : {
      "common" : {
        "type" : "record",
        "fields" : [ ]
      },
      "oldCommon" : {
        "type" : "record",
        "fields" : [ ]
      },
      "fabrics" : { },
      "instances" : { },
      "selected" : "default",
      "nonEditable" : [ ],
      "isSubscribedPipelineWithPipelineConfigs" : false
    },
    "sparkConf" : [ ],
    "hadoopConf" : [ ],
    "codeMode" : "sparse",
    "buildSystem" : "maven",
    "externalDependencies" : [ ],
    "dependentProjectExternalDependencies" : [ {
      "projectUID" : "12654",
      "projectName" : "ProphecySparkBasicsPython",
      "externalDependencies" : [ ]
    }, {
      "projectUID" : "12656",
      "projectName" : "ProphecyStreamingPython",
      "externalDependencies" : [ ]
    }, {
      "projectUID" : "12655",
      "projectName" : "ProphecyWarehousePython",
      "externalDependencies" : [ ]
    } ],
    "isImported" : false,
    "interimMode" : "Full",
    "interimModeEnabled" : true,
    "visualCodeInterimMode" : "Disabled",
    "recordsLimit" : {
      "enabled" : false,
      "value" : 1000
    },
    "topLevelPackage" : "filepathparse",
    "configurationVersion" : "v2"
  },
  "connections" : [ {
    "id" : "dzNREkI_Xi_nXm0xO8EKx$$D5Uva_v5Mx-GVYlBocEFA",
    "source" : "si43ZXH6H972iMwui5vhK$$SfEhI81Y6lnUXriZDsR5z",
    "sourcePort" : "x2RFJfw-gUYOhF_zkYo0Q$$WuuNyAXIwVuwjfBieZk_X",
    "target" : "nCNazYD-EvaVktR_78sHe$$i3CDJ-_oWp_GnrmbvqMqz",
    "targetPort" : "ikxDaN4rUruj3dBiAsbEq$$svVZXsBxjwK-PtZqUy98I"
  } ],
  "processes" : {
    "nCNazYD-EvaVktR_78sHe$$i3CDJ-_oWp_GnrmbvqMqz" : {
      "id" : "nCNazYD-EvaVktR_78sHe$$i3CDJ-_oWp_GnrmbvqMqz",
      "component" : "SchemaTransform",
      "metadata" : {
        "label" : "SchemaTransform_1",
        "slug" : "SchemaTransform_1",
        "x" : -100,
        "y" : -60,
        "phase" : 0,
        "cache" : false,
        "detailedStats" : false,
        "isImported" : false,
        "comment" : "Enhances customer claim data by adding file path and split information for better traceability.",
        "autoUpdateComment" : true
      },
      "ports" : {
        "inputs" : [ {
          "id" : "ikxDaN4rUruj3dBiAsbEq$$svVZXsBxjwK-PtZqUy98I",
          "slug" : "customer_claim_file",
          "schema" : {
            "type" : "struct",
            "fields" : [ {
              "name" : "batchid",
              "type" : "integer",
              "nullable" : true,
              "metadata" : {
                "description" : "Unique identifier for each batch of data processed.",
                "mappings" : [ ],
                "tags" : [ ]
              }
            }, {
              "name" : "insertdate",
              "type" : "timestamp",
              "nullable" : true,
              "metadata" : {
                "description" : "Timestamp indicating when the batch was inserted into the system; Format is ISO 8601.",
                "mappings" : [ ],
                "tags" : [ ]
              }
            }, {
              "name" : "status",
              "type" : "integer",
              "nullable" : true,
              "metadata" : {
                "description" : "Current status of the batch process; Indicates the state of the batch, such as in progress or completed.",
                "mappings" : [ ],
                "tags" : [ ]
              }
            }, {
              "name" : "process",
              "type" : "string",
              "nullable" : true,
              "metadata" : {
                "description" : "Name of the process associated with the batch; Indicates the specific operation being performed, such as claim ingestion.",
                "mappings" : [ ],
                "tags" : [ ]
              }
            }, {
              "name" : "batch_status_check",
              "type" : "integer",
              "nullable" : true,
              "metadata" : {
                "description" : "Indicator of the current status of the batch process; Helps in monitoring the progress of the batch ingestion.",
                "mappings" : [ ],
                "tags" : [ ]
              }
            } ]
          },
          "isStreaming" : false
        } ],
        "outputs" : [ {
          "id" : "uHcXK6yYYXdRQ17aaCjxB$$7OeToO808it0Mvhf96BiQ",
          "slug" : "out",
          "schema" : {
            "type" : "struct",
            "fields" : [ {
              "name" : "batchid",
              "type" : "integer",
              "nullable" : true,
              "metadata" : {
                "description" : "",
                "mappings" : [ ],
                "tags" : [ ]
              }
            }, {
              "name" : "insertdate",
              "type" : "timestamp",
              "nullable" : true,
              "metadata" : {
                "description" : "",
                "mappings" : [ ],
                "tags" : [ ]
              }
            }, {
              "name" : "status",
              "type" : "integer",
              "nullable" : true,
              "metadata" : {
                "description" : "",
                "mappings" : [ ],
                "tags" : [ ]
              }
            }, {
              "name" : "process",
              "type" : "string",
              "nullable" : true,
              "metadata" : {
                "description" : "",
                "mappings" : [ ],
                "tags" : [ ]
              }
            }, {
              "name" : "batch_status_check",
              "type" : "integer",
              "nullable" : true,
              "metadata" : {
                "description" : "",
                "mappings" : [ ],
                "tags" : [ ]
              }
            }, {
              "name" : "file_input_path",
              "type" : "string",
              "nullable" : false,
              "metadata" : {
                "description" : "",
                "mappings" : [ ],
                "tags" : [ ]
              }
            }, {
              "name" : "file_input_split",
              "type" : {
                "type" : "array",
                "elementType" : "string",
                "containsNull" : false
              },
              "nullable" : false,
              "metadata" : {
                "description" : "",
                "mappings" : [ ],
                "tags" : [ ]
              }
            } ]
          },
          "isStreaming" : false
        } ],
        "selectedInputFields" : [ ],
        "isCustomOutputSchema" : true,
        "autoUpdateOnRun" : true
      },
      "properties" : {
        "importLanguage" : "sql",
        "importString" : "",
        "transformations" : [ {
          "AddRule" : {
            "expression" : {
              "expression" : "",
              "format" : "python"
            },
            "param_errors" : [ ]
          },
          "MissingColumn" : {
            "sourceColumn" : "",
            "defaultValue" : {
              "expression" : "",
              "format" : "python"
            }
          },
          "DropColumn" : {
            "sourceColumn" : ""
          },
          "kind" : "AddReplaceColumn",
          "RenameColumn" : {
            "sourceColumn" : "",
            "targetColumn" : ""
          },
          "AddReplaceColumn" : {
            "sourceColumn" : "file_input_path",
            "expression" : {
              "format" : "sql",
              "expression" : "expr(\"_metadata.file_path\")"
            }
          }
        }, {
          "AddRule" : {
            "expression" : {
              "expression" : "",
              "format" : "python"
            },
            "param_errors" : [ ]
          },
          "MissingColumn" : {
            "sourceColumn" : "",
            "defaultValue" : {
              "expression" : "",
              "format" : "python"
            }
          },
          "DropColumn" : {
            "sourceColumn" : ""
          },
          "kind" : "AddReplaceColumn",
          "RenameColumn" : {
            "sourceColumn" : "",
            "targetColumn" : ""
          },
          "AddReplaceColumn" : {
            "sourceColumn" : "file_input_split",
            "expression" : {
              "format" : "sql",
              "expression" : "split(file_input_path, \"/\" )"
            }
          }
        } ],
        "activeTab" : "transformations",
        "columnsSelector" : [ ]
      },
      "componentInfo" : {
        "gemId" : "gitUri=http://gitserver:3000/DxEheDCJ_team_5751/DxEheDCJ_project_12654.git&subPath=&tag=0.2.30&projectSubscriptionProjectId=12654&path=gems/SchemaTransform",
        "projectName" : "ProphecySparkBasicsPython"
      }
    },
    "si43ZXH6H972iMwui5vhK$$SfEhI81Y6lnUXriZDsR5z" : {
      "id" : "si43ZXH6H972iMwui5vhK$$SfEhI81Y6lnUXriZDsR5z",
      "component" : "Source",
      "metadata" : {
        "label" : "raw_control_batch",
        "slug" : "raw_control_batch",
        "x" : -360,
        "y" : -60,
        "phase" : 0,
        "cache" : false,
        "detailedStats" : false,
        "isImported" : false,
        "comment" : "Loads batch processing data from a CSV file for monitoring and analysis of batch operations.",
        "autoUpdateComment" : true
      },
      "ports" : {
        "inputs" : [ ],
        "outputs" : [ {
          "id" : "x2RFJfw-gUYOhF_zkYo0Q$$WuuNyAXIwVuwjfBieZk_X",
          "slug" : "out"
        } ],
        "selectedInputFields" : [ ],
        "isCustomOutputSchema" : false,
        "autoUpdateOnRun" : false
      },
      "properties" : {
        "datasetId" : "datasets/raw_control_batch"
      }
    }
  },
  "ports" : {
    "inputs" : [ ],
    "outputs" : [ ],
    "selectedInputFields" : [ ],
    "isCustomOutputSchema" : false,
    "autoUpdateOnRun" : false
  }
}